registry/__init__.py
registry/__main__.py
registry/extract_comprehensive.py
registry/extract_from_html.py
registry/extract_with_versioning.py
registry/fetch_html.py
registry/fetch_pdfs.py
registry/extraction/__init__.py
registry/extraction/model_curator.py
registry/extraction/pdf_parser.py
llmring_registry-0.1.0.dist-info/METADATA
llmring_registry-0.1.0.dist-info/WHEEL
llmring_registry-0.1.0.dist-info/entry_points.txt
llmring_registry-0.1.0.dist-info/licenses/LICENSE
llmring_registry-0.1.0.dist-info/RECORD
