Metadata-Version: 2.4
Name: llmring-registry
Version: 0.1.0
Summary: LLMRing public model registry CLI and tools (manual curation workflow)
Project-URL: Homepage, https://llmring.ai
Project-URL: Repository, https://github.com/llmring/registry
Project-URL: Issues, https://github.com/llmring/registry/issues
Author-email: Juan Reyero <juan@juanreyero.com>
License: MIT License
License-File: LICENSE
Keywords: cli,llm,llmring,models,pricing,registry
Classifier: Intended Audience :: Developers
Classifier: License :: OSI Approved :: MIT License
Classifier: Programming Language :: Python
Classifier: Programming Language :: Python :: 3
Classifier: Programming Language :: Python :: 3.13
Classifier: Topic :: Software Development :: Libraries
Classifier: Topic :: Utilities
Requires-Python: >=3.13
Requires-Dist: beautifulsoup4>=4.13.4
Requires-Dist: click>=8.2.1
Requires-Dist: playwright>=1.54.0
Requires-Dist: python-dotenv>=1.1.1
Requires-Dist: requests>=2.32.4
Provides-Extra: playwright
Requires-Dist: playwright>=1.45.0; extra == 'playwright'
